netdecom/Convex_hull_DAG.py
netdecom/Graph_gererators.py
netdecom/__init__.py
netdecom/decom_h.cp39-win_amd64.pyd
netdecom/examples.py
netdecom/Release/decom_h.pyd
netdecom/Release/iconv-2.dll
netdecom/Release/igraph.dll
netdecom/Release/libdecom_h.so
netdecom/Release/libgcc_s_seh-1.dll
netdecom/Release/libgfortran-5.dll
netdecom/Release/liblapack.dll
netdecom/Release/libquadmath-0.dll
netdecom/Release/libwinpthread-1.dll
netdecom/Release/libxml2.dll
netdecom/Release/openblas.dll
netdecom/Release/zlib1.dll
netdecom/examples/Animal-Network.txt
netdecom/examples/CA-CondMat.txt
netdecom/examples/CA-HepTh.txt
netdecom/examples/Email-Enron.txt
netdecom/examples/as20000102.txt
netdecom/examples/bio-CE-GN.txt
netdecom/examples/bio-CE-GT.txt
netdecom/examples/bio-DR-CX.txt
netdecom/examples/mammalia-voles-rob-trapping-22.txt
netdecom/examples/rec-amazon.txt
netdecom/examples/rec-eachmovie.txt
netdecom/examples/rec-movielens-tag-movies-10m.txt
netdecom/examples/rec-movielens-user-movies-10m.txt
netdecom/examples/rec-movielens.txt
netdecom/examples/rec-yelp-user-business.txt
netdecom-0.0.5.5.dist-info/METADATA
netdecom-0.0.5.5.dist-info/WHEEL
netdecom-0.0.5.5.dist-info/top_level.txt
netdecom-0.0.5.5.dist-info/RECORD
