Metadata-Version: 2.4
Name: netdecom
Version: 0.0.5.5
Summary: Dimensionality Reduction and Decomposition of Undirected Graph Models and Bayesian Networks
Author: Hugh
Classifier: Programming Language :: Python :: 3
Classifier: Programming Language :: Python :: 3.9
Classifier: License :: OSI Approved :: MIT License
Classifier: Operating System :: OS Independent
Dynamic: author
Dynamic: classifier
Dynamic: description
Dynamic: description-content-type
Dynamic: summary
